mintql/__init__.py
mintql-0.0.1.dist-info/LICENSE
mintql-0.0.1.dist-info/METADATA
mintql-0.0.1.dist-info/WHEEL
mintql-0.0.1.dist-info/RECORD
