Metadata-Version: 2.3
Name: mintql
Version: 0.0.1
Summary: A minimalist Python library for building SQL queries safely and elegantly
License: MIT
Keywords: sql,query,builder,database,orm
Author: Thomas Fazzari
Requires-Python: >=3.8,<4.0
Classifier: Development Status :: 4 - Beta
Classifier: Intended Audience :: Developers
Classifier: License :: OSI Approved :: MIT License
Classifier: Programming Language :: Python :: 3
Classifier: Programming Language :: Python :: 3.8
Classifier: Programming Language :: Python :: 3.9
Classifier: Programming Language :: Python :: 3.10
Classifier: Programming Language :: Python :: 3.11
Classifier: Programming Language :: Python :: 3.12
Classifier: Programming Language :: Python :: 3.13
Classifier: Topic :: Database
Classifier: Topic :: Software Development :: Libraries :: Python Modules
Project-URL: Homepage, https://github.com/thomasfazzari1/mintql
Project-URL: Repository, https://github.com/thomasfazzari1/mintql
